LICENSE
MANIFEST.in
README.md
pyproject.toml
requirements-dev.txt
requirements.txt
setup.py
backend_clone/__init__.py
backend_clone/cli.py
backend_clone/config.py
backend_clone/generator.py
backend_clone/tasks.py
backend_clone/utils.py
backend_clone.egg-info/PKG-INFO
backend_clone.egg-info/SOURCES.txt
backend_clone.egg-info/dependency_links.txt
backend_clone.egg-info/entry_points.txt
backend_clone.egg-info/not-zip-safe
backend_clone.egg-info/requires.txt
backend_clone.egg-info/top_level.txt
backend_clone/core/__init__.py
backend_clone/core/ai_engine.py
backend_clone/core/cloud.py
backend_clone/core/framework.py
backend_clone/core/generator.py
backend_clone/core/performance.py
backend_clone/core/security.py
backend_clone/templates/fastapi/main.py.j2
backend_clone/templates/fastapi/requirements.txt.j2
backend_clone/templates/fastapi/models/__init__.py.j2
backend_clone/templates/fastapi/models/book.py.j2
backend_clone/templates/fastapi/routes/__init__.py.j2
backend_clone/templates/fastapi/routes/books.py.j2
examples/basic_usage.py
examples/full_app.py
tests/test_backend_clone.py
tests/test_import.py
webclone_backend/__init__.py
webclone_backend/api/__init__.py
webclone_backend/auth/__init__.py
webclone_backend/auth/jwt_handler.py
webclone_backend/auth/password.py
webclone_backend/core/__init__.py
webclone_backend/core/app.py
webclone_backend/database/__init__.py
webclone_backend/database/connection.py
webclone_backend/database/models.py
webclone_backend/storage/__init__.py
webclone_backend/storage/cache.py
webclone_backend/storage/file_manager.py
webclone_backend/storage/image_processor.py
webclone_backend/utils/__init__.py
webclone_backend/utils/validators.py