Metadata-Version: 2.4
Name: backend-clone
Version: 2.0.0
Summary: 🚀 Ultimate Backend Generator - AI-powered, multi-framework, cloud-ready, production-grade
Home-page: https://github.com/backend-clone/backend-clone
Author: Backend Clone Team
Author-email: Backend Clone Team <team@backend-clone.dev>
License: MIT
Project-URL: Homepage, https://github.com/backend-clone/backend-clone
Project-URL: Documentation, https://docs.backend-clone.dev
Project-URL: Repository, https://github.com/backend-clone/backend-clone
Project-URL: Issues, https://github.com/backend-clone/backend-clone/issues
Project-URL: Changelog, https://github.com/backend-clone/backend-clone/blob/main/CHANGELOG.md
Platform: any
Classifier: Development Status :: 5 - Production/Stable
Classifier: Intended Audience :: Developers
Classifier: Topic :: Software Development :: Code Generators
Classifier: Topic :: Software Development :: Build Tools
Classifier: Topic :: Internet :: WWW/HTTP :: WSGI :: Application
Classifier: License :: OSI Approved :: MIT License
Classifier: Programming Language :: Python :: 3
Classifier: Programming Language :: Python :: 3.8
Classifier: Programming Language :: Python :: 3.9
Classifier: Programming Language :: Python :: 3.10
Classifier: Programming Language :: Python :: 3.11
Classifier: Programming Language :: Python :: 3.12
Classifier: Operating System :: OS Independent
Classifier: Environment :: Console
Classifier: Natural Language :: English
Requires-Python: >=3.9
License-File: LICENSE
Requires-Dist: click>=8.1.7
Requires-Dist: rich>=13.7.0
Requires-Dist: inquirer>=3.1.4
Requires-Dist: requests>=2.31.0
Requires-Dist: httpx>=0.25.0
Requires-Dist: aiohttp>=3.9.0
Requires-Dist: jinja2>=3.1.2
Requires-Dist: pyyaml>=6.0.1
Requires-Dist: gitpython>=3.1.40
Requires-Dist: openai>=1.3.0
Requires-Dist: anthropic>=0.7.0
Requires-Dist: pathspec>=0.11.0
Requires-Dist: watchdog>=3.0.0
Requires-Dist: pydantic>=2.5.0
Requires-Dist: jsonschema>=4.20.0
Requires-Dist: tqdm>=4.66.0
Requires-Dist: prompt-toolkit>=3.0.0
Requires-Dist: python-dotenv>=1.0.0
Requires-Dist: toml>=0.10.2
Requires-Dist: semver>=3.0.0
Requires-Dist: fastapi>=0.104.0
Requires-Dist: uvicorn>=0.24.0
Requires-Dist: sqlalchemy>=2.0.0
Requires-Dist: alembic>=1.13.0
Provides-Extra: dev
Requires-Dist: pytest>=7.4.0; extra == "dev"
Requires-Dist: pytest-cov>=4.1.0; extra == "dev"
Requires-Dist: pytest-asyncio>=0.21.0; extra == "dev"
Requires-Dist: pytest-mock>=3.12.0; extra == "dev"
Requires-Dist: black>=23.11.0; extra == "dev"
Requires-Dist: flake8>=6.1.0; extra == "dev"
Requires-Dist: isort>=5.12.0; extra == "dev"
Requires-Dist: mypy>=1.7.0; extra == "dev"
Requires-Dist: pylint>=3.0.0; extra == "dev"
Requires-Dist: bandit>=1.7.5; extra == "dev"
Requires-Dist: safety>=2.3.5; extra == "dev"
Requires-Dist: sphinx>=7.2.0; extra == "dev"
Requires-Dist: sphinx-rtd-theme>=2.0.0; extra == "dev"
Requires-Dist: sphinx-click>=5.1.0; extra == "dev"
Requires-Dist: build>=1.0.0; extra == "dev"
Requires-Dist: twine>=4.0.0; extra == "dev"
Provides-Extra: all
Requires-Dist: gunicorn>=21.2.0; extra == "all"
Requires-Dist: redis>=5.0.0; extra == "all"
Requires-Dist: celery>=5.3.0; extra == "all"
Requires-Dist: boto3>=1.34.0; extra == "all"
Requires-Dist: google-cloud-storage>=2.10.0; extra == "all"
Requires-Dist: azure-storage-blob>=12.19.0; extra == "all"
Dynamic: author
Dynamic: home-page
Dynamic: license-file
Dynamic: platform
Dynamic: requires-python
